{
  "id": "session-1755875763410-44881c64",
  "start_time": "2025-08-22T15:16:03.410Z",
  "interactions": 2,
  "kg_checks": [
    {
      "interaction": 1,
      "timestamp": "2025-08-22T15:16:03.782Z",
      "query": "ES Module CommonJS configuration",
      "results_count": 19,
      "linear_results_count": 14,
      "warnings_count": 2,
      "compliance_met": true
    }
  ],
  "issue_logs": [],
  "solution_logs": [],
  "compliance_status": "compliant",
  "violations": [],
  "interaction_log": [
    {
      "number": 1,
      "type": "task_analysis_start",
      "description": "ES Module CommonJS configuration",
      "timestamp": "2025-08-22T15:16:03.417Z",
      "data": {}
    },
    {
      "number": 2,
      "type": "kg_check",
      "description": "Checked KG for: \"ES Module CommonJS configuration\"",
      "timestamp": "2025-08-22T15:16:03.782Z",
      "data": {
        "results_count": 19,
        "warnings_count": 2
      }
    }
  ]
}